actions_tool_kit/__init__.py
actions_tool_kit/__main__.py
actions_tool_kit/actions_core.py
gh_actions_tool_kit-0.1.1.dist-info/licenses/LICENSE
gh_actions_tool_kit-0.1.1.dist-info/METADATA
gh_actions_tool_kit-0.1.1.dist-info/WHEEL
gh_actions_tool_kit-0.1.1.dist-info/entry_points.txt
gh_actions_tool_kit-0.1.1.dist-info/top_level.txt
gh_actions_tool_kit-0.1.1.dist-info/RECORD
