Metadata-Version: 2.4
Name: gh-actions-tool-kit
Version: 0.1.1
Summary: Tiny actions/core-style helpers for Python GitHub Actions
Author: Akash B
Maintainer-email: Akash B <akashbasa8@gmail.com>
License-Expression: MIT
Requires-Python: >=3.8
License-File: LICENSE
Provides-Extra: dev
Requires-Dist: pytest>=8; extra == "dev"
Requires-Dist: mypy>=1.10; extra == "dev"
Requires-Dist: types-setuptools; extra == "dev"
Dynamic: license-file
